elasticsearch7_dsl/__init__.py
elasticsearch7_dsl/aggs.py
elasticsearch7_dsl/analysis.py
elasticsearch7_dsl/connections.py
elasticsearch7_dsl/document.py
elasticsearch7_dsl/exceptions.py
elasticsearch7_dsl/faceted_search.py
elasticsearch7_dsl/field.py
elasticsearch7_dsl/function.py
elasticsearch7_dsl/index.py
elasticsearch7_dsl/mapping.py
elasticsearch7_dsl/query.py
elasticsearch7_dsl/search.py
elasticsearch7_dsl/serializer.py
elasticsearch7_dsl/update_by_query.py
elasticsearch7_dsl/utils.py
elasticsearch7_dsl/wrappers.py
elasticsearch7_dsl/response/__init__.py
elasticsearch7_dsl/response/aggs.py
elasticsearch7_dsl/response/hit.py
elasticsearch7_dsl_p/__init__.py
elasticsearch7_dsl_p/aggs.py
elasticsearch7_dsl_p/analysis.py
elasticsearch7_dsl_p/connections.py
elasticsearch7_dsl_p/document.py
elasticsearch7_dsl_p/exceptions.py
elasticsearch7_dsl_p/faceted_search.py
elasticsearch7_dsl_p/field.py
elasticsearch7_dsl_p/function.py
elasticsearch7_dsl_p/index.py
elasticsearch7_dsl_p/mapping.py
elasticsearch7_dsl_p/query.py
elasticsearch7_dsl_p/search.py
elasticsearch7_dsl_p/serializer.py
elasticsearch7_dsl_p/update_by_query.py
elasticsearch7_dsl_p/utils.py
elasticsearch7_dsl_p/wrappers.py
elasticsearch7_dsl_p/response/__init__.py
elasticsearch7_dsl_p/response/aggs.py
elasticsearch7_dsl_p/response/hit.py
elasticsearch7_dslp/__init__.py
elasticsearch7_dslp/aggs.py
elasticsearch7_dslp/analysis.py
elasticsearch7_dslp/connections.py
elasticsearch7_dslp/document.py
elasticsearch7_dslp/exceptions.py
elasticsearch7_dslp/faceted_search.py
elasticsearch7_dslp/field.py
elasticsearch7_dslp/function.py
elasticsearch7_dslp/index.py
elasticsearch7_dslp/mapping.py
elasticsearch7_dslp/query.py
elasticsearch7_dslp/search.py
elasticsearch7_dslp/serializer.py
elasticsearch7_dslp/update_by_query.py
elasticsearch7_dslp/utils.py
elasticsearch7_dslp/wrappers.py
elasticsearch7_dslp/response/__init__.py
elasticsearch7_dslp/response/aggs.py
elasticsearch7_dslp/response/hit.py
elasticsearch7_dsl_p-7.4.1.dist-info/AUTHORS
elasticsearch7_dsl_p-7.4.1.dist-info/LICENSE
elasticsearch7_dsl_p-7.4.1.dist-info/METADATA
elasticsearch7_dsl_p-7.4.1.dist-info/WHEEL
elasticsearch7_dsl_p-7.4.1.dist-info/top_level.txt
elasticsearch7_dsl_p-7.4.1.dist-info/RECORD
